[
  {
    "KEY": "DRAFT",
    "TITLE": "Draft",
    "SHORT": "Draft",
    "DEF": "Preliminary versions of a written work for iterated critique and revision",
    "CONTRIB": "Boris STEIPE <boris.steipe@utoronto.ca>",
    "VERSION": "v. 2023-05-21",
    "UPDATE": "2023-05-21T17:00-0400",
    "STATUS": "stub",
    "STYLE": "show:TRUE; col:#E1EEE5; size:10; order:140",
    "META": "",
    "PARENT.KEY": "WRTSK",
    "PARENT.NOTES": "Reference tree: IS-A relationship.",
    "ISA.KEYS": "",
    "ISA.NOTES": "",
    "RESULTSFROM.KEYS": "",
    "RESULTSFROM.NOTES": "",
    "GOVERNEDBY.KEYS": "",
    "GOVERNEDBY.NOTES": "",
    "COMPONENTOF.KEYS": "",
    "COMPONENTOF.NOTES": "",
    "TASK": "The Drafting Tasks pattern supports the refining of students' ideas through preliminary versions of a written work. Enhancing the quality of the final product is the central goal, achieved by iteratively improving structure, content, and clarity. Challenges can include unclear expectations and lack of guidance. Address these by providing clear expectations, offering consistent guidance, and delivering constructive feedback to optimize drafting tasks.",
    "DETAILS": "",
    "AI": "",
    "IMPLEMENTATION": "",
    "CANBEREPLACEDWITH.KEYS": "",
    "CANBEREPLACEDWITH.NOTES": "",
    "FIGURE.URL": "",
    "FIGURE.CAPTION": "",
    "HASCOMPONENT.KEYS": "",
    "HASCOMPONENT.NOTES": "",
    "ALTERNATIVEFORM.KEYS": "",
    "ALTERNATIVEFORM.NOTES": "",
    "RESULTSIN.KEYS": "",
    "RESULTSIN.NOTES": ""
  }
]
