[
  {
    "KEY": "VOLOP",
    "TITLE": "Volunteering Opportunities",
    "SHORT": "Volunteering",
    "DEF": "Organized to strengthen community relations and promote social values among participants",
    "CONTRIB": "Boris STEIPE <boris.steipe@utoronto.ca>",
    "VERSION": "v. 2023-05-21",
    "UPDATE": "2023-05-21T17:00-0400",
    "STATUS": "stub",
    "STYLE": "show:FALSE; col:#E1EEE5; size:10; order:73",
    "META": "",
    "PARENT.KEY": "EXCUR",
    "PARENT.NOTES": "Reference tree: IS-A relationship.",
    "ISA.KEYS": "",
    "ISA.NOTES": "",
    "RESULTSFROM.KEYS": "",
    "RESULTSFROM.NOTES": "",
    "GOVERNEDBY.KEYS": "",
    "GOVERNEDBY.NOTES": "",
    "COMPONENTOF.KEYS": "",
    "COMPONENTOF.NOTES": "",
    "TASK": "The Volunteering Opportunities pattern aims to develop civic responsibility. To optimize VOLUN, connect students with relevant organizations, endorse participation in diverse opportunities, and support reflection on the volunteering experiences. AI can aid in connecting students with suitable volunteering opportunities.",
    "DETAILS": "",
    "AI": "",
    "IMPLEMENTATION": "",
    "CANBEREPLACEDWITH.KEYS": "",
    "CANBEREPLACEDWITH.NOTES": "",
    "FIGURE.URL": "",
    "FIGURE.CAPTION": "",
    "HASCOMPONENT.KEYS": "",
    "HASCOMPONENT.NOTES": "",
    "ALTERNATIVEFORM.KEYS": "",
    "ALTERNATIVEFORM.NOTES": "",
    "RESULTSIN.KEYS": "",
    "RESULTSIN.NOTES": ""
  }
]
